LICENSE
MANIFEST.in
cbf.py
setup.cfg
setup.py
cbf.egg-info/PKG-INFO
cbf.egg-info/SOURCES.txt
cbf.egg-info/dependency_links.txt
cbf.egg-info/requires.txt
cbf.egg-info/top_level.txt
src/cbf.cpp
src/cbf.h
src/python-cbf.c
src/python-cbf.h