Metadata-Version: 2.1
Name: cbf
Version: 1.2.0
Summary: CBF Bindings for Python
Home-page: https://github.com/paulscherrerinstitute/cbf
Author: Paul Scherrer Institute
Classifier: Programming Language :: C
Classifier: Programming Language :: Python
Classifier: Programming Language :: Python :: 3
License-File: LICENSE
